asta_s_eu/scraping/core/__init__.py
asta_s_eu/scraping/core/config.py
asta_s_eu/scraping/core/decorators.py
asta_s_eu/scraping/core/helper.py
asta_s_eu/scraping/core/log.py
asta_s_eu/scraping/core/prospects.jinja2.html
asta_s_eu/scraping/core/py.typed
asta_s_eu/scraping/core/send_email.py
asta_s_eu/scraping/core/typing.py
asta_s_eu/scraping/core/prospect_database/__init__.py
asta_s_eu/scraping/core/prospect_database/dynamo_db.py
asta_s_eu/scraping/core/prospect_database/local_file_system.py
asta_s_eu/scraping/core/selenium/__init__.py
asta_s_eu/scraping/core/selenium/base_classes.py
asta_s_eu/scraping/core/selenium/env.py
asta_s_eu_scraping_core-0.0.6.dist-info/METADATA
asta_s_eu_scraping_core-0.0.6.dist-info/WHEEL
asta_s_eu_scraping_core-0.0.6.dist-info/top_level.txt
asta_s_eu_scraping_core-0.0.6.dist-info/RECORD
