Metadata-Version: 2.4
Name: asta-s-eu-scraping-core
Version: 0.0.6
Author-email: Andrei Danciuc <python.ciur@gmail.com>
License-Expression: MIT
Requires-Python: ==3.13.2
Requires-Dist: boto3==1.34.39
Requires-Dist: ciur==0.2.3
Requires-Dist: jinja2==3.1.6
Requires-Dist: python-dotenv==1.0.1
Requires-Dist: pyyaml==6.0.1
Requires-Dist: retry==0.9.2
Provides-Extra: ui
Requires-Dist: selenium==4.14.0; extra == "ui"
Provides-Extra: dev
Requires-Dist: ciur[dev]==0.2.3; extra == "dev"
Provides-Extra: otel
Requires-Dist: opentelemetry-distro==0.55b1; extra == "otel"
Requires-Dist: opentelemetry-exporter-otlp==1.34.1; extra == "otel"
